MANIFEST.in
README.rst
main.py
setup.cfg
setup.py
uwsgi.ini
blessed_extensions/__init__.py
blessed_extensions/admin.py
blessed_extensions/archive_comment_versions.py
blessed_extensions/auth_tkt_identity_policy.py
blessed_extensions/capture_author.py
blessed_extensions/capture_email.py
blessed_extensions/capture_remote_addr.py
blessed_extensions/capture_website.py
blessed_extensions/cors.py
blessed_extensions/csrf_token.py
blessed_extensions/isso_client_shim.py
blessed_extensions/markdown_renderer.py
blessed_extensions/mod_email.py
blessed_extensions/moderation.py
blessed_extensions/profiler.py
blessed_extensions/proxyfix.py
blessed_extensions/route_list.py
blessed_extensions/setup.py
blessed_extensions/unix_time_json_encoder.py
blessed_extensions/validate_comment_len.py
blessed_extensions/voting.py
blessed_extensions/admin_static/layout.css
blessed_extensions/admin_templates/base.html
ext_migrations/README.rst
ext_migrations/alembic.ini
ext_migrations/env.py
ext_migrations/versions/18d88bc2c83_add_unique_index_for_voting.py
isso/README.rst
isso/js/count.dev.js
isso/js/count.min.js
isso/js/embed.dev.js
isso/js/embed.min.js
migrations/README.rst
migrations/alembic.ini
migrations/env.py
migrations/versions/46a03f51647_.py
pg_discuss/__init__.py
pg_discuss/_compat.py
pg_discuss/app.py
pg_discuss/auth_forms.py
pg_discuss/config.py
pg_discuss/db.py
pg_discuss/ext.py
pg_discuss/forms.py
pg_discuss/identity.py
pg_discuss/management.py
pg_discuss/models.py
pg_discuss/queries.py
pg_discuss/serialize.py
pg_discuss/tables.py
pg_discuss/utils.py
pg_discuss/views.py
pg_discuss.egg-info/PKG-INFO
pg_discuss.egg-info/SOURCES.txt
pg_discuss.egg-info/dependency_links.txt
pg_discuss.egg-info/entry_points.txt
pg_discuss.egg-info/not-zip-safe
pg_discuss.egg-info/requires.txt
pg_discuss.egg-info/top_level.txt
pg_discuss/drivers/__init__.py
pg_discuss/drivers/escaping_renderer.py
pg_discuss/drivers/iso_date_json_encoder.py
pg_discuss/drivers/null_identity_policy.py
pg_discuss/static/embed.min.js
pg_discuss/static/pg-discuss.svg
pg_discuss/templates/landing.html
pg_discuss/templates/login.html
tests/__init__.py