Metadata-Version: 1.1
Name: pg-discuss
Version: 1.0b1
Summary: A comment system backend on top of PostgreSQL
Home-page: https://pg-discuss.sprin.io
Author: Steffen Prince
Author-email: steffen@sprin.io
License: MIT
Download-URL: https://github.com/sprin/pg-discuss
Platform: Any
Classifier: Development Status :: 4 - Beta
Classifier: License :: OSI Approved :: MIT License
Classifier: Programming Language :: Python
Classifier: Programming Language :: Python :: 2
Classifier: Programming Language :: Python :: 2.7
Classifier: Programming Language :: Python :: 3
Classifier: Programming Language :: Python :: 3.4
Classifier: Programming Language :: Python :: 3.5
Classifier: Intended Audience :: Developers
Classifier: Environment :: Web Environment
Classifier: Framework :: Flask
Provides: pg_discuss
